<?xml version="1.0"?>
<log>
	<record id="0" timestamp="2014-Apr-10 23:51:17.419649">XML log record 0</record>
	<record id="1" timestamp="2014-Apr-10 23:51:17.419932">XML log record 1</record>
	<record id="2" timestamp="2014-Apr-10 23:51:17.419974">XML log record 2</record>
	<record id="3" timestamp="2014-Apr-10 23:51:17.420001">XML log record 3</record>
	<record id="4" timestamp="2014-Apr-10 23:51:17.420026">XML log record 4</record>
	<record id="5" timestamp="2014-Apr-10 23:51:17.420051">XML log record 5</record>
	<record id="6" timestamp="2014-Apr-10 23:51:17.420075">XML log record 6</record>
	<record id="7" timestamp="2014-Apr-10 23:51:17.420100">XML log record 7</record>
	<record id="8" timestamp="2014-Apr-10 23:51:17.420125">XML log record 8</record>
	<record id="9" timestamp="2014-Apr-10 23:51:17.420149">XML log record 9</record>
	<record id="10" timestamp="2014-Apr-10 23:51:17.420174">XML log record 10</record>
	<record id="11" timestamp="2014-Apr-10 23:51:17.420199">XML log record 11</record>
	<record id="12" timestamp="2014-Apr-10 23:51:17.420223">XML log record 12</record>
	<record id="13" timestamp="2014-Apr-10 23:51:17.420247">XML log record 13</record>
	<record id="14" timestamp="2014-Apr-10 23:51:17.420272">XML log record 14</record>
	<record id="15" timestamp="2014-Apr-10 23:51:17.420297">XML log record 15</record>
	<record id="16" timestamp="2014-Apr-10 23:51:17.420329">XML log record 16</record>
	<record id="17" timestamp="2014-Apr-10 23:51:17.420353">XML log record 17</record>
	<record id="18" timestamp="2014-Apr-10 23:51:17.420377">XML log record 18</record>
	<record id="19" timestamp="2014-Apr-10 23:51:17.420401">XML log record 19</record>
	<record id="20" timestamp="2014-Apr-10 23:51:17.420425">XML log record 20</record>
	<record id="21" timestamp="2014-Apr-10 23:51:17.420449">XML log record 21</record>
	<record id="22" timestamp="2014-Apr-10 23:51:17.420544">XML log record 22</record>
	<record id="23" timestamp="2014-Apr-10 23:51:17.420569">XML log record 23</record>
	<record id="24" timestamp="2014-Apr-10 23:51:17.420593">XML log record 24</record>
	<record id="25" timestamp="2014-Apr-10 23:51:17.420617">XML log record 25</record>
	<record id="26" timestamp="2014-Apr-10 23:51:17.420641">XML log record 26</record>
	<record id="27" timestamp="2014-Apr-10 23:51:17.420665">XML log record 27</record>
	<record id="28" timestamp="2014-Apr-10 23:51:17.420689">XML log record 28</record>
	<record id="29" timestamp="2014-Apr-10 23:51:17.420713">XML log record 29</record>
	<record id="30" timestamp="2014-Apr-10 23:51:17.420737">XML log record 30</record>
	<record id="31" timestamp="2014-Apr-10 23:51:17.420761">XML log record 31</record>
	<record id="32" timestamp="2014-Apr-10 23:51:17.420785">XML log record 32</record>
	<record id="33" timestamp="2014-Apr-10 23:51:17.420809">XML log record 33</record>
	<record id="34" timestamp="2014-Apr-10 23:51:17.420832">XML log record 34</record>
	<record id="35" timestamp="2014-Apr-10 23:51:17.420856">XML log record 35</record>
	<record id="36" timestamp="2014-Apr-10 23:51:17.420880">XML log record 36</record>
	<record id="37" timestamp="2014-Apr-10 23:51:17.420903">XML log record 37</record>
	<record id="38" timestamp="2014-Apr-10 23:51:17.420931">XML log record 38</record>
	<record id="39" timestamp="2014-Apr-10 23:51:17.420956">XML log record 39</record>
	<record id="40" timestamp="2014-Apr-10 23:51:17.420980">XML log record 40</record>
	<record id="41" timestamp="2014-Apr-10 23:51:17.421004">XML log record 41</record>
	<record id="42" timestamp="2014-Apr-10 23:51:17.421028">XML log record 42</record>
	<record id="43" timestamp="2014-Apr-10 23:51:17.421052">XML log record 43</record>
	<record id="44" timestamp="2014-Apr-10 23:51:17.421076">XML log record 44</record>
	<record id="45" timestamp="2014-Apr-10 23:51:17.421100">XML log record 45</record>
	<record id="46" timestamp="2014-Apr-10 23:51:17.421124">XML log record 46</record>
	<record id="47" timestamp="2014-Apr-10 23:51:17.421147">XML log record 47</record>
	<record id="48" timestamp="2014-Apr-10 23:51:17.421171">XML log record 48</record>
	<record id="49" timestamp="2014-Apr-10 23:51:17.421195">XML log record 49</record>
	<record id="50" timestamp="2014-Apr-10 23:51:17.421218">XML log record 50</record>
	<record id="51" timestamp="2014-Apr-10 23:51:17.421242">XML log record 51</record>
	<record id="52" timestamp="2014-Apr-10 23:51:17.421266">XML log record 52</record>
	<record id="53" timestamp="2014-Apr-10 23:51:17.421290">XML log record 53</record>
	<record id="54" timestamp="2014-Apr-10 23:51:17.421313">XML log record 54</record>
	<record id="55" timestamp="2014-Apr-10 23:51:17.421337">XML log record 55</record>
	<record id="56" timestamp="2014-Apr-10 23:51:17.421361">XML log record 56</record>
	<record id="57" timestamp="2014-Apr-10 23:51:17.421384">XML log record 57</record>
	<record id="58" timestamp="2014-Apr-10 23:51:17.421408">XML log record 58</record>
	<record id="59" timestamp="2014-Apr-10 23:51:17.421432">XML log record 59</record>
	<record id="60" timestamp="2014-Apr-10 23:51:17.421530">XML log record 60</record>
	<record id="61" timestamp="2014-Apr-10 23:51:17.421620">XML log record 61</record>
	<record id="62" timestamp="2014-Apr-10 23:51:17.421681">XML log record 62</record>
	<record id="63" timestamp="2014-Apr-10 23:51:17.421740">XML log record 63</record>
	<record id="64" timestamp="2014-Apr-10 23:51:17.421789">XML log record 64</record>
	<record id="65" timestamp="2014-Apr-10 23:51:17.421839">XML log record 65</record>
	<record id="66" timestamp="2014-Apr-10 23:51:17.421880">XML log record 66</record>
	<record id="67" timestamp="2014-Apr-10 23:51:17.421929">XML log record 67</record>
	<record id="68" timestamp="2014-Apr-10 23:51:17.421994">XML log record 68</record>
	<record id="69" timestamp="2014-Apr-10 23:51:17.422043">XML log record 69</record>
	<record id="70" timestamp="2014-Apr-10 23:51:17.422109">XML log record 70</record>
	<record id="71" timestamp="2014-Apr-10 23:51:17.422159">XML log record 71</record>
	<record id="72" timestamp="2014-Apr-10 23:51:17.422217">XML log record 72</record>
	<record id="73" timestamp="2014-Apr-10 23:51:17.422259">XML log record 73</record>
	<record id="74" timestamp="2014-Apr-10 23:51:17.422317">XML log record 74</record>
	<record id="75" timestamp="2014-Apr-10 23:51:17.422351">XML log record 75</record>
	<record id="76" timestamp="2014-Apr-10 23:51:17.422376">XML log record 76</record>
	<record id="77" timestamp="2014-Apr-10 23:51:17.422409">XML log record 77</record>
	<record id="78" timestamp="2014-Apr-10 23:51:17.422433">XML log record 78</record>
	<record id="79" timestamp="2014-Apr-10 23:51:17.422506">XML log record 79</record>
	<record id="80" timestamp="2014-Apr-10 23:51:17.422531">XML log record 80</record>
	<record id="81" timestamp="2014-Apr-10 23:51:17.422557">XML log record 81</record>
	<record id="82" timestamp="2014-Apr-10 23:51:17.422581">XML log record 82</record>
	<record id="83" timestamp="2014-Apr-10 23:51:17.422607">XML log record 83</record>
	<record id="84" timestamp="2014-Apr-10 23:51:17.422632">XML log record 84</record>
	<record id="85" timestamp="2014-Apr-10 23:51:17.422657">XML log record 85</record>
	<record id="86" timestamp="2014-Apr-10 23:51:17.422682">XML log record 86</record>
	<record id="87" timestamp="2014-Apr-10 23:51:17.422707">XML log record 87</record>
	<record id="88" timestamp="2014-Apr-10 23:51:17.422732">XML log record 88</record>
	<record id="89" timestamp="2014-Apr-10 23:51:17.422757">XML log record 89</record>
	<record id="90" timestamp="2014-Apr-10 23:51:17.422782">XML log record 90</record>
	<record id="91" timestamp="2014-Apr-10 23:51:17.422807">XML log record 91</record>
	<record id="92" timestamp="2014-Apr-10 23:51:17.422832">XML log record 92</record>
	<record id="93" timestamp="2014-Apr-10 23:51:17.422857">XML log record 93</record>
	<record id="94" timestamp="2014-Apr-10 23:51:17.422882">XML log record 94</record>
	<record id="95" timestamp="2014-Apr-10 23:51:17.422907">XML log record 95</record>
	<record id="96" timestamp="2014-Apr-10 23:51:17.422932">XML log record 96</record>
	<record id="97" timestamp="2014-Apr-10 23:51:17.422957">XML log record 97</record>
	<record id="98" timestamp="2014-Apr-10 23:51:17.423004">XML log record 98</record>
	<record id="99" timestamp="2014-Apr-10 23:51:17.423033">XML log record 99</record>
	<record id="100" timestamp="2014-Apr-10 23:51:17.423059">XML log record 100</record>
	<record id="101" timestamp="2014-Apr-10 23:51:17.423084">XML log record 101</record>
	<record id="102" timestamp="2014-Apr-10 23:51:17.423109">XML log record 102</record>
	<record id="103" timestamp="2014-Apr-10 23:51:17.423135">XML log record 103</record>
	<record id="104" timestamp="2014-Apr-10 23:51:17.423160">XML log record 104</record>
	<record id="105" timestamp="2014-Apr-10 23:51:17.423185">XML log record 105</record>
	<record id="106" timestamp="2014-Apr-10 23:51:17.423211">XML log record 106</record>
	<record id="107" timestamp="2014-Apr-10 23:51:17.423236">XML log record 107</record>
	<record id="108" timestamp="2014-Apr-10 23:51:17.423261">XML log record 108</record>
	<record id="109" timestamp="2014-Apr-10 23:51:17.423286">XML log record 109</record>
	<record id="110" timestamp="2014-Apr-10 23:51:17.423311">XML log record 110</record>
	<record id="111" timestamp="2014-Apr-10 23:51:17.423337">XML log record 111</record>
	<record id="112" timestamp="2014-Apr-10 23:51:17.423362">XML log record 112</record>
	<record id="113" timestamp="2014-Apr-10 23:51:17.423387">XML log record 113</record>
	<record id="114" timestamp="2014-Apr-10 23:51:17.423412">XML log record 114</record>
	<record id="115" timestamp="2014-Apr-10 23:51:17.423457">XML log record 115</record>
	<record id="116" timestamp="2014-Apr-10 23:51:17.423485">XML log record 116</record>
	<record id="117" timestamp="2014-Apr-10 23:51:17.423511">XML log record 117</record>
	<record id="118" timestamp="2014-Apr-10 23:51:17.423536">XML log record 118</record>
	<record id="119" timestamp="2014-Apr-10 23:51:17.423561">XML log record 119</record>
	<record id="120" timestamp="2014-Apr-10 23:51:17.423586">XML log record 120</record>
	<record id="121" timestamp="2014-Apr-10 23:51:17.423611">XML log record 121</record>
	<record id="122" timestamp="2014-Apr-10 23:51:17.423636">XML log record 122</record>
	<record id="123" timestamp="2014-Apr-10 23:51:17.423661">XML log record 123</record>
	<record id="124" timestamp="2014-Apr-10 23:51:17.423686">XML log record 124</record>
	<record id="125" timestamp="2014-Apr-10 23:51:17.423711">XML log record 125</record>
	<record id="126" timestamp="2014-Apr-10 23:51:17.423735">XML log record 126</record>
	<record id="127" timestamp="2014-Apr-10 23:51:17.423760">XML log record 127</record>
	<record id="128" timestamp="2014-Apr-10 23:51:17.423786">XML log record 128</record>
	<record id="129" timestamp="2014-Apr-10 23:51:17.423811">XML log record 129</record>
	<record id="130" timestamp="2014-Apr-10 23:51:17.423835">XML log record 130</record>
	<record id="131" timestamp="2014-Apr-10 23:51:17.423860">XML log record 131</record>
	<record id="132" timestamp="2014-Apr-10 23:51:17.423885">XML log record 132</record>
	<record id="133" timestamp="2014-Apr-10 23:51:17.423910">XML log record 133</record>
	<record id="134" timestamp="2014-Apr-10 23:51:17.423935">XML log record 134</record>
	<record id="135" timestamp="2014-Apr-10 23:51:17.423960">XML log record 135</record>
	<record id="136" timestamp="2014-Apr-10 23:51:17.423985">XML log record 136</record>
	<record id="137" timestamp="2014-Apr-10 23:51:17.424010">XML log record 137</record>
	<record id="138" timestamp="2014-Apr-10 23:51:17.424035">XML log record 138</record>
	<record id="139" timestamp="2014-Apr-10 23:51:17.424060">XML log record 139</record>
	<record id="140" timestamp="2014-Apr-10 23:51:17.424085">XML log record 140</record>
	<record id="141" timestamp="2014-Apr-10 23:51:17.424109">XML log record 141</record>
	<record id="142" timestamp="2014-Apr-10 23:51:17.424134">XML log record 142</record>
	<record id="143" timestamp="2014-Apr-10 23:51:17.424159">XML log record 143</record>
	<record id="144" timestamp="2014-Apr-10 23:51:17.424184">XML log record 144</record>
	<record id="145" timestamp="2014-Apr-10 23:51:17.424209">XML log record 145</record>
	<record id="146" timestamp="2014-Apr-10 23:51:17.424234">XML log record 146</record>
	<record id="147" timestamp="2014-Apr-10 23:51:17.424259">XML log record 147</record>
	<record id="148" timestamp="2014-Apr-10 23:51:17.424284">XML log record 148</record>
	<record id="149" timestamp="2014-Apr-10 23:51:17.424309">XML log record 149</record>
	<record id="150" timestamp="2014-Apr-10 23:51:17.424334">XML log record 150</record>
	<record id="151" timestamp="2014-Apr-10 23:51:17.424359">XML log record 151</record>
	<record id="152" timestamp="2014-Apr-10 23:51:17.424383">XML log record 152</record>
	<record id="153" timestamp="2014-Apr-10 23:51:17.424408">XML log record 153</record>
	<record id="154" timestamp="2014-Apr-10 23:51:17.424453">XML log record 154</record>
	<record id="155" timestamp="2014-Apr-10 23:51:17.424486">XML log record 155</record>
	<record id="156" timestamp="2014-Apr-10 23:51:17.424512">XML log record 156</record>
	<record id="157" timestamp="2014-Apr-10 23:51:17.424537">XML log record 157</record>
	<record id="158" timestamp="2014-Apr-10 23:51:17.424562">XML log record 158</record>
	<record id="159" timestamp="2014-Apr-10 23:51:17.424587">XML log record 159</record>
	<record id="160" timestamp="2014-Apr-10 23:51:17.424612">XML log record 160</record>
	<record id="161" timestamp="2014-Apr-10 23:51:17.424637">XML log record 161</record>
	<record id="162" timestamp="2014-Apr-10 23:51:17.424662">XML log record 162</record>
	<record id="163" timestamp="2014-Apr-10 23:51:17.424687">XML log record 163</record>
	<record id="164" timestamp="2014-Apr-10 23:51:17.424712">XML log record 164</record>
	<record id="165" timestamp="2014-Apr-10 23:51:17.424737">XML log record 165</record>
	<record id="166" timestamp="2014-Apr-10 23:51:17.424762">XML log record 166</record>
	<record id="167" timestamp="2014-Apr-10 23:51:17.424787">XML log record 167</record>
	<record id="168" timestamp="2014-Apr-10 23:51:17.424812">XML log record 168</record>
	<record id="169" timestamp="2014-Apr-10 23:51:17.424837">XML log record 169</record>
	<record id="170" timestamp="2014-Apr-10 23:51:17.424862">XML log record 170</record>
	<record id="171" timestamp="2014-Apr-10 23:51:17.424887">XML log record 171</record>
	<record id="172" timestamp="2014-Apr-10 23:51:17.424912">XML log record 172</record>
	<record id="173" timestamp="2014-Apr-10 23:51:17.424937">XML log record 173</record>
	<record id="174" timestamp="2014-Apr-10 23:51:17.424962">XML log record 174</record>
	<record id="175" timestamp="2014-Apr-10 23:51:17.424987">XML log record 175</record>
	<record id="176" timestamp="2014-Apr-10 23:51:17.425012">XML log record 176</record>
	<record id="177" timestamp="2014-Apr-10 23:51:17.425037">XML log record 177</record>
	<record id="178" timestamp="2014-Apr-10 23:51:17.425062">XML log record 178</record>
	<record id="179" timestamp="2014-Apr-10 23:51:17.425087">XML log record 179</record>
	<record id="180" timestamp="2014-Apr-10 23:51:17.425112">XML log record 180</record>
	<record id="181" timestamp="2014-Apr-10 23:51:17.425137">XML log record 181</record>
	<record id="182" timestamp="2014-Apr-10 23:51:17.425162">XML log record 182</record>
	<record id="183" timestamp="2014-Apr-10 23:51:17.425186">XML log record 183</record>
	<record id="184" timestamp="2014-Apr-10 23:51:17.425211">XML log record 184</record>
	<record id="185" timestamp="2014-Apr-10 23:51:17.425236">XML log record 185</record>
	<record id="186" timestamp="2014-Apr-10 23:51:17.425261">XML log record 186</record>
	<record id="187" timestamp="2014-Apr-10 23:51:17.425286">XML log record 187</record>
	<record id="188" timestamp="2014-Apr-10 23:51:17.425311">XML log record 188</record>
	<record id="189" timestamp="2014-Apr-10 23:51:17.425336">XML log record 189</record>
	<record id="190" timestamp="2014-Apr-10 23:51:17.425360">XML log record 190</record>
	<record id="191" timestamp="2014-Apr-10 23:51:17.425385">XML log record 191</record>
</log>
